[
  {
    "question": "If all cats are mammals, and some mammals are dogs, which of the following is true?",
    "answers": [
      "All cats are dogs",
      "Some dogs are cats",
      "All mammals are cats",
      "Some mammals could be dogs"
    ],
    "correct_answer": "Some mammals could be dogs",
    "category": "Logic",
    "explanation": "Only the last statement is logically valid based on the premises."
  },
  {
    "question": "Tom is taller than Jerry. Jerry is taller than Mike. Who is the shortest?",
    "answers": [
      "Tom",
      "Jerry",
      "Mike",
      "Can't determine"
    ],
    "correct_answer": "Mike",
    "category": "Logic",
    "explanation": "If Tom > Jerry > Mike, Mike is the shortest."
  },
  {
    "question": "What is the square root of 144?",
    "answers": [
      "10",
      "11",
      "12",
      "14"
    ],
    "correct_answer": "12",
    "category": "Math",
    "explanation": "12 x 12 = 144."
  },
  {
    "question": "What is 15% of 200?",
    "answers": [
      "25",
      "30",
      "35",
      "40"
    ],
    "correct_answer": "30",
    "category": "Math",
    "explanation": "0.15 \u00d7 200 = 30."
  },
  {
    "question": "What comes next in the sequence: 3, 6, 12, 24, ?",
    "answers": [
      "36",
      "48",
      "50",
      "60"
    ],
    "correct_answer": "48",
    "category": "Patterns",
    "explanation": "Each number doubles the previous: \u00d72 pattern."
  },
  {
    "question": "Which number is missing? 5, 10, __, 20, 25",
    "answers": [
      "12",
      "15",
      "13",
      "18"
    ],
    "correct_answer": "15",
    "category": "Patterns",
    "explanation": "Increments of 5: 5, 10, 15, 20, 25."
  },
  {
    "question": "Which word is the opposite of 'expand'?",
    "answers": [
      "Extend",
      "Grow",
      "Contract",
      "Increase"
    ],
    "correct_answer": "Contract",
    "category": "Verbal",
    "explanation": "'Contract' means to shrink or reduce."
  },
  {
    "question": "Choose the analogy: Book is to Reading as Fork is to?",
    "answers": [
      "Drawing",
      "Writing",
      "Stirring",
      "Eating"
    ],
    "correct_answer": "Eating",
    "category": "Verbal",
    "explanation": "You read with a book and eat with a fork."
  },
  {
    "question": "Find the odd one out: \u25b2, \u25a0, \u25cf, \u2605",
    "answers": [
      "\u25cf",
      "\u25b2",
      "\u25a0",
      "\u2605"
    ],
    "correct_answer": "\u2605",
    "category": "Abstract",
    "explanation": "\u2605 is a complex shape; the others are basic geometric figures."
  },
  {
    "question": "Which image would logically follow this pattern? [\u25b2\u25b6\u25b2\u25b6__]",
    "answers": [
      "\u25b2",
      "\u25b6",
      "\u25a0",
      "\u25cf"
    ],
    "correct_answer": "\u25b2",
    "category": "Abstract",
    "explanation": "The pattern alternates: \u25b2, \u25b6, \u25b2, \u25b6, ..."
  },
  {
    "question": "If all cats are mammals, and some mammals are dogs, which of the following is true?",
    "answers": [
      "All cats are dogs",
      "Some dogs are cats",
      "All mammals are cats",
      "Some mammals could be dogs"
    ],
    "correct_answer": "Some mammals could be dogs",
    "category": "Logic",
    "explanation": "Only the last statement is logically valid based on the premises."
  },
  {
    "question": "Tom is taller than Jerry. Jerry is taller than Mike. Who is the shortest?",
    "answers": [
      "Tom",
      "Jerry",
      "Mike",
      "Can't determine"
    ],
    "correct_answer": "Mike",
    "category": "Logic",
    "explanation": "If Tom > Jerry > Mike, Mike is the shortest."
  },
  {
    "question": "What is the square root of 144?",
    "answers": [
      "10",
      "11",
      "12",
      "14"
    ],
    "correct_answer": "12",
    "category": "Math",
    "explanation": "12 x 12 = 144."
  },
  {
    "question": "What is 15% of 200?",
    "answers": [
      "25",
      "30",
      "35",
      "40"
    ],
    "correct_answer": "30",
    "category": "Math",
    "explanation": "0.15 \u00d7 200 = 30."
  },
  {
    "question": "What comes next in the sequence: 3, 6, 12, 24, ?",
    "answers": [
      "36",
      "48",
      "50",
      "60"
    ],
    "correct_answer": "48",
    "category": "Patterns",
    "explanation": "Each number doubles the previous: \u00d72 pattern."
  },
  {
    "question": "Which number is missing? 5, 10, __, 20, 25",
    "answers": [
      "12",
      "15",
      "13",
      "18"
    ],
    "correct_answer": "15",
    "category": "Patterns",
    "explanation": "Increments of 5: 5, 10, 15, 20, 25."
  },
  {
    "question": "Which word is the opposite of 'expand'?",
    "answers": [
      "Extend",
      "Grow",
      "Contract",
      "Increase"
    ],
    "correct_answer": "Contract",
    "category": "Verbal",
    "explanation": "'Contract' means to shrink or reduce."
  },
  {
    "question": "Choose the analogy: Book is to Reading as Fork is to?",
    "answers": [
      "Drawing",
      "Writing",
      "Stirring",
      "Eating"
    ],
    "correct_answer": "Eating",
    "category": "Verbal",
    "explanation": "You read with a book and eat with a fork."
  },
  {
    "question": "Find the odd one out: \u25b2, \u25a0, \u25cf, \u2605",
    "answers": [
      "\u25cf",
      "\u25b2",
      "\u25a0",
      "\u2605"
    ],
    "correct_answer": "\u2605",
    "category": "Abstract",
    "explanation": "\u2605 is a complex shape; the others are basic geometric figures."
  },
  {
    "question": "Which image would logically follow this pattern? [\u25b2\u25b6\u25b2\u25b6__]",
    "answers": [
      "\u25b2",
      "\u25b6",
      "\u25a0",
      "\u25cf"
    ],
    "correct_answer": "\u25b2",
    "category": "Abstract",
    "explanation": "The pattern alternates: \u25b2, \u25b6, \u25b2, \u25b6, ..."
  },
  {
    "question": "If all cats are mammals, and some mammals are dogs, which of the following is true?",
    "answers": [
      "All cats are dogs",
      "Some dogs are cats",
      "All mammals are cats",
      "Some mammals could be dogs"
    ],
    "correct_answer": "Some mammals could be dogs",
    "category": "Logic",
    "explanation": "Only the last statement is logically valid based on the premises."
  },
  {
    "question": "Tom is taller than Jerry. Jerry is taller than Mike. Who is the shortest?",
    "answers": [
      "Tom",
      "Jerry",
      "Mike",
      "Can't determine"
    ],
    "correct_answer": "Mike",
    "category": "Logic",
    "explanation": "If Tom > Jerry > Mike, Mike is the shortest."
  },
  {
    "question": "What is the square root of 144?",
    "answers": [
      "10",
      "11",
      "12",
      "14"
    ],
    "correct_answer": "12",
    "category": "Math",
    "explanation": "12 x 12 = 144."
  },
  {
    "question": "What is 15% of 200?",
    "answers": [
      "25",
      "30",
      "35",
      "40"
    ],
    "correct_answer": "30",
    "category": "Math",
    "explanation": "0.15 \u00d7 200 = 30."
  },
  {
    "question": "What comes next in the sequence: 3, 6, 12, 24, ?",
    "answers": [
      "36",
      "48",
      "50",
      "60"
    ],
    "correct_answer": "48",
    "category": "Patterns",
    "explanation": "Each number doubles the previous: \u00d72 pattern."
  },
  {
    "question": "Which number is missing? 5, 10, __, 20, 25",
    "answers": [
      "12",
      "15",
      "13",
      "18"
    ],
    "correct_answer": "15",
    "category": "Patterns",
    "explanation": "Increments of 5: 5, 10, 15, 20, 25."
  },
  {
    "question": "Which word is the opposite of 'expand'?",
    "answers": [
      "Extend",
      "Grow",
      "Contract",
      "Increase"
    ],
    "correct_answer": "Contract",
    "category": "Verbal",
    "explanation": "'Contract' means to shrink or reduce."
  },
  {
    "question": "Choose the analogy: Book is to Reading as Fork is to?",
    "answers": [
      "Drawing",
      "Writing",
      "Stirring",
      "Eating"
    ],
    "correct_answer": "Eating",
    "category": "Verbal",
    "explanation": "You read with a book and eat with a fork."
  },
  {
    "question": "Find the odd one out: \u25b2, \u25a0, \u25cf, \u2605",
    "answers": [
      "\u25cf",
      "\u25b2",
      "\u25a0",
      "\u2605"
    ],
    "correct_answer": "\u2605",
    "category": "Abstract",
    "explanation": "\u2605 is a complex shape; the others are basic geometric figures."
  },
  {
    "question": "Which image would logically follow this pattern? [\u25b2\u25b6\u25b2\u25b6__]",
    "answers": [
      "\u25b2",
      "\u25b6",
      "\u25a0",
      "\u25cf"
    ],
    "correct_answer": "\u25b2",
    "category": "Abstract",
    "explanation": "The pattern alternates: \u25b2, \u25b6, \u25b2, \u25b6, ..."
  },
  {
    "question": "If all cats are mammals, and some mammals are dogs, which of the following is true?",
    "answers": [
      "All cats are dogs",
      "Some dogs are cats",
      "All mammals are cats",
      "Some mammals could be dogs"
    ],
    "correct_answer": "Some mammals could be dogs",
    "category": "Logic",
    "explanation": "Only the last statement is logically valid based on the premises."
  },
  {
    "question": "Tom is taller than Jerry. Jerry is taller than Mike. Who is the shortest?",
    "answers": [
      "Tom",
      "Jerry",
      "Mike",
      "Can't determine"
    ],
    "correct_answer": "Mike",
    "category": "Logic",
    "explanation": "If Tom > Jerry > Mike, Mike is the shortest."
  },
  {
    "question": "What is the square root of 144?",
    "answers": [
      "10",
      "11",
      "12",
      "14"
    ],
    "correct_answer": "12",
    "category": "Math",
    "explanation": "12 x 12 = 144."
  },
  {
    "question": "What is 15% of 200?",
    "answers": [
      "25",
      "30",
      "35",
      "40"
    ],
    "correct_answer": "30",
    "category": "Math",
    "explanation": "0.15 \u00d7 200 = 30."
  },
  {
    "question": "What comes next in the sequence: 3, 6, 12, 24, ?",
    "answers": [
      "36",
      "48",
      "50",
      "60"
    ],
    "correct_answer": "48",
    "category": "Patterns",
    "explanation": "Each number doubles the previous: \u00d72 pattern."
  },
  {
    "question": "Which number is missing? 5, 10, __, 20, 25",
    "answers": [
      "12",
      "15",
      "13",
      "18"
    ],
    "correct_answer": "15",
    "category": "Patterns",
    "explanation": "Increments of 5: 5, 10, 15, 20, 25."
  },
  {
    "question": "Which word is the opposite of 'expand'?",
    "answers": [
      "Extend",
      "Grow",
      "Contract",
      "Increase"
    ],
    "correct_answer": "Contract",
    "category": "Verbal",
    "explanation": "'Contract' means to shrink or reduce."
  },
  {
    "question": "Choose the analogy: Book is to Reading as Fork is to?",
    "answers": [
      "Drawing",
      "Writing",
      "Stirring",
      "Eating"
    ],
    "correct_answer": "Eating",
    "category": "Verbal",
    "explanation": "You read with a book and eat with a fork."
  },
  {
    "question": "Find the odd one out: \u25b2, \u25a0, \u25cf, \u2605",
    "answers": [
      "\u25cf",
      "\u25b2",
      "\u25a0",
      "\u2605"
    ],
    "correct_answer": "\u2605",
    "category": "Abstract",
    "explanation": "\u2605 is a complex shape; the others are basic geometric figures."
  },
  {
    "question": "Which image would logically follow this pattern? [\u25b2\u25b6\u25b2\u25b6__]",
    "answers": [
      "\u25b2",
      "\u25b6",
      "\u25a0",
      "\u25cf"
    ],
    "correct_answer": "\u25b2",
    "category": "Abstract",
    "explanation": "The pattern alternates: \u25b2, \u25b6, \u25b2, \u25b6, ..."
  },
  {
    "question": "If all cats are mammals, and some mammals are dogs, which of the following is true?",
    "answers": [
      "All cats are dogs",
      "Some dogs are cats",
      "All mammals are cats",
      "Some mammals could be dogs"
    ],
    "correct_answer": "Some mammals could be dogs",
    "category": "Logic",
    "explanation": "Only the last statement is logically valid based on the premises."
  },
  {
    "question": "Tom is taller than Jerry. Jerry is taller than Mike. Who is the shortest?",
    "answers": [
      "Tom",
      "Jerry",
      "Mike",
      "Can't determine"
    ],
    "correct_answer": "Mike",
    "category": "Logic",
    "explanation": "If Tom > Jerry > Mike, Mike is the shortest."
  },
  {
    "question": "What is the square root of 144?",
    "answers": [
      "10",
      "11",
      "12",
      "14"
    ],
    "correct_answer": "12",
    "category": "Math",
    "explanation": "12 x 12 = 144."
  },
  {
    "question": "What is 15% of 200?",
    "answers": [
      "25",
      "30",
      "35",
      "40"
    ],
    "correct_answer": "30",
    "category": "Math",
    "explanation": "0.15 \u00d7 200 = 30."
  },
  {
    "question": "What comes next in the sequence: 3, 6, 12, 24, ?",
    "answers": [
      "36",
      "48",
      "50",
      "60"
    ],
    "correct_answer": "48",
    "category": "Patterns",
    "explanation": "Each number doubles the previous: \u00d72 pattern."
  },
  {
    "question": "Which number is missing? 5, 10, __, 20, 25",
    "answers": [
      "12",
      "15",
      "13",
      "18"
    ],
    "correct_answer": "15",
    "category": "Patterns",
    "explanation": "Increments of 5: 5, 10, 15, 20, 25."
  },
  {
    "question": "Which word is the opposite of 'expand'?",
    "answers": [
      "Extend",
      "Grow",
      "Contract",
      "Increase"
    ],
    "correct_answer": "Contract",
    "category": "Verbal",
    "explanation": "'Contract' means to shrink or reduce."
  },
  {
    "question": "Choose the analogy: Book is to Reading as Fork is to?",
    "answers": [
      "Drawing",
      "Writing",
      "Stirring",
      "Eating"
    ],
    "correct_answer": "Eating",
    "category": "Verbal",
    "explanation": "You read with a book and eat with a fork."
  },
  {
    "question": "Find the odd one out: \u25b2, \u25a0, \u25cf, \u2605",
    "answers": [
      "\u25cf",
      "\u25b2",
      "\u25a0",
      "\u2605"
    ],
    "correct_answer": "\u2605",
    "category": "Abstract",
    "explanation": "\u2605 is a complex shape; the others are basic geometric figures."
  },
  {
    "question": "Which image would logically follow this pattern? [\u25b2\u25b6\u25b2\u25b6__]",
    "answers": [
      "\u25b2",
      "\u25b6",
      "\u25a0",
      "\u25cf"
    ],
    "correct_answer": "\u25b2",
    "category": "Abstract",
    "explanation": "The pattern alternates: \u25b2, \u25b6, \u25b2, \u25b6, ..."
  }
]